nano_arpes_browser/__init__.py
nano_arpes_browser/core/__init__.py
nano_arpes_browser/core/models.py
nano_arpes_browser/core/io/__init__.py
nano_arpes_browser/core/io/exporters.py
nano_arpes_browser/core/io/loaders.py
nano_arpes_browser/core/processing/__init__.py
nano_arpes_browser/core/processing/kspace.py
nano_arpes_browser/gui/__init__.py
nano_arpes_browser/gui/app.py
nano_arpes_browser/gui/main_window.py
nano_arpes_browser/gui/styles.py
nano_arpes_browser/gui/widgets/__init__.py
nano_arpes_browser/gui/widgets/arpes_viewer.py
nano_arpes_browser/gui/widgets/control_panels.py
nano_arpes_browser/gui/widgets/spatial_viewer.py
nano_arpes_browser-0.1.0.dist-info/METADATA
nano_arpes_browser-0.1.0.dist-info/WHEEL
nano_arpes_browser-0.1.0.dist-info/entry_points.txt
nano_arpes_browser-0.1.0.dist-info/top_level.txt
nano_arpes_browser-0.1.0.dist-info/RECORD
