Metadata-Version: 2.4
Name: nano-arpes-browser
Version: 0.1.0
Summary: nano-ARPES data browser and analysis tool
Author-email: Boris Senkovskiy <81705695+senkovskiy@users.noreply.github.com>
License: MIT
Project-URL: Homepage, https://github.com/senkovskiy/nano-arpes-browser
Project-URL: Documentation, https://github.com/senkovskiy/nano-arpes-browser#readme
Project-URL: Repository, https://github.com/senkovskiy/nano-arpes-browser
Project-URL: Issues, https://github.com/senkovskiy/nano-arpes-browser/issues
Keywords: ARPES,nano-ARPES,micro-ARPES,photoemission,spectroscopy,synchrotron,Soleil
Classifier: Development Status :: 4 - Beta
Classifier: Intended Audience :: Science/Research
Classifier: Topic :: Scientific/Engineering :: Physics
Classifier: License :: OSI Approved :: MIT License
Classifier: Programming Language :: Python :: 3.10
Classifier: Programming Language :: Python :: 3.11
Classifier: Programming Language :: Python :: 3.12
Classifier: Operating System :: OS Independent
Classifier: Environment :: X11 Applications :: Qt
Requires-Python: >=3.10
Requires-Dist: numpy>=1.24
Requires-Dist: scipy>=1.10
Requires-Dist: h5py>=3.8
Requires-Dist: PyQt6>=6.5
Requires-Dist: pyqtgraph>=0.13
Requires-Dist: pydantic>=2.0
Requires-Dist: pytest>=9.0.2
Provides-Extra: dev
Requires-Dist: pytest>=7.0; extra == "dev"
Requires-Dist: pytest-qt>=4.2; extra == "dev"
Requires-Dist: pytest-cov>=4.0; extra == "dev"
Requires-Dist: ruff>=0.4; extra == "dev"
Requires-Dist: mypy>=1.0; extra == "dev"
Requires-Dist: pyinstaller>=6.0; extra == "dev"
Requires-Dist: pre-commit>=3.0; extra == "dev"
Requires-Dist: build>=1.0; extra == "dev"
Requires-Dist: twine>=5.0; extra == "dev"
